{
  "mcpServers": {
    "coree": {
      "command": "npx",
      "args": ["--yes", "@coree-ai/coree@0.13.0", "serve"],
      "env": {
        "COREE__MEMORY__REMOTE_AUTH_TOKEN": "${COREE__MEMORY__REMOTE_AUTH_TOKEN}",
        "COREE__MEMORY__REMOTE_URL": "${COREE__MEMORY__REMOTE_URL}",
        "COREE__INDEX__REMOTE_AUTH_TOKEN": "${COREE__INDEX__REMOTE_AUTH_TOKEN}",
        "COREE__INDEX__REMOTE_URL": "${COREE__INDEX__REMOTE_URL}",
        "COREE_BINARY_OVERRIDE": "${COREE_BINARY_OVERRIDE}",
        "COREE_MODEL_DIR": "${COREE_MODEL_DIR}"
      }
    }
  }
}
